dntdb/README.md
dntdb/__init__.py
dntdb/env.json
dntdb/main.so
dntdb/mysearch.so
dntdb/requirements.txt
dntdb/setup.py
dntdb/test.so
dntdb/__pycache__/__init__.cpython-38.pyc
dntdb/__pycache__/mysearch.cpython-38.pyc
dntdb/__pycache__/search.cpython-38.pyc
dntdb/config/__init__.py
dntdb/config/config.dev.yaml
dntdb/config/loader.so
dntdb/config/__pycache__/loader.cpython-38.pyc
dntdb/config/__pycache__/loader.cpython-39.pyc
dntdb/logs/__init__.py
dntdb/logs/log_handler.so
dntdb/logs/__pycache__/log_handler.cpython-38.pyc
dntdb/logs/__pycache__/log_handler.cpython-39.pyc
dntdb/logs/logging/MySearch.log
dntdb/logs/logging/__init__.py
dntdb/utils/__init__.py
dntdb/utils/checker.so
dntdb/utils/faiss_db.so
dntdb/utils/helper.so
dntdb/utils/index_db.so
dntdb/utils/info_db.so
dntdb/utils/redis_utils.so
dntdb/utils/__pycache__/checker.cpython-38.pyc
dntdb/utils/__pycache__/faiss_db.cpython-38.pyc
dntdb/utils/__pycache__/helper.cpython-38.pyc
dntdb/utils/__pycache__/index_db.cpython-38.pyc
dntdb/utils/__pycache__/info_db.cpython-38.pyc
dntdb/utils/__pycache__/redis_utils.cpython-38.pyc
dntdb-1.0.4.data/data/dntdb/MySearch.log
dntdb-1.0.4.data/data/dntdb/README.md
dntdb-1.0.4.data/data/dntdb/__init__.cpython-38.pyc
dntdb-1.0.4.data/data/dntdb/checker.cpython-38.pyc
dntdb-1.0.4.data/data/dntdb/checker.so
dntdb-1.0.4.data/data/dntdb/config.dev.yaml
dntdb-1.0.4.data/data/dntdb/env.json
dntdb-1.0.4.data/data/dntdb/faiss_db.cpython-38.pyc
dntdb-1.0.4.data/data/dntdb/faiss_db.so
dntdb-1.0.4.data/data/dntdb/helper.cpython-38.pyc
dntdb-1.0.4.data/data/dntdb/helper.so
dntdb-1.0.4.data/data/dntdb/index_db.cpython-38.pyc
dntdb-1.0.4.data/data/dntdb/index_db.so
dntdb-1.0.4.data/data/dntdb/info_db.cpython-38.pyc
dntdb-1.0.4.data/data/dntdb/info_db.so
dntdb-1.0.4.data/data/dntdb/loader.cpython-38.pyc
dntdb-1.0.4.data/data/dntdb/loader.cpython-39.pyc
dntdb-1.0.4.data/data/dntdb/loader.so
dntdb-1.0.4.data/data/dntdb/log_handler.cpython-38.pyc
dntdb-1.0.4.dist-info/METADATA
dntdb-1.0.4.dist-info/WHEEL
dntdb-1.0.4.dist-info/top_level.txt
dntdb-1.0.4.dist-info/RECORD
