Metadata-Version: 2.1
Name: dntdb
Version: 1.0.4
Summary: Search Engine
Author: DNT
Classifier: Programming Language :: Python :: 3
Classifier: License :: OSI Approved :: MIT License
Classifier: Operating System :: OS Independent
Requires-Dist: faiss-gpu (==1.7.2)
Requires-Dist: numpy (==1.24.4)
Requires-Dist: opencv-python (==4.8.0.76)
Requires-Dist: pytz (==2023.3.post1)
Requires-Dist: PyYAML (==6.0.1)
Requires-Dist: redis (==5.0.0)
Requires-Dist: setuptools (==68.0.0)
Requires-Dist: Shapely (==2.0.3)
